LICENSE
MANIFEST.in
README.md
setup.cfg
setup.py
ekankthdevx/__init__.py
ekankthdevx/config.py
ekankthdevx.egg-info/PKG-INFO
ekankthdevx.egg-info/SOURCES.txt
ekankthdevx.egg-info/dependency_links.txt
ekankthdevx.egg-info/requires.txt
ekankthdevx.egg-info/top_level.txt
ekankthdevx/Clients/__init__.py
ekankthdevx/Clients/client.py
ekankthdevx/Clients/pytgcalls.py
ekankthdevx/blacklist/__init__.py
ekankthdevx/blacklist/support.py
ekankthdevx/button/__init__.py
ekankthdevx/button/button.py
ekankthdevx/extra/__init__.py
ekankthdevx/extra/hosted.py
ekankthdevx/help/__init__.py
ekankthdevx/help/help.py
ekankthdevx/helper/__init__.py
ekankthdevx/helper/basic.py
ekankthdevx/helper/call.py
ekankthdevx/helper/data.py
ekankthdevx/helper/ekankth.py
ekankthdevx/helper/goblok.py
ekankthdevx/helper/hacking.py
ekankthdevx/helper/inline.py
ekankthdevx/helper/interval.py
ekankthdevx/helper/parser.py
ekankthdevx/helper/repo.py
ekankthdevx/helper/sticker.py
ekankthdevx/helper/tools.py
ekankthdevx/helper/utility.py
ekankthdevx/helper/what.py
ekankthdevx/methods/__init__.py
ekankthdevx/methods/queue.py
ekankthdevx/py_trans/__init__.py
ekankthdevx/py_trans/async_translator.py
ekankthdevx/py_trans/errors.py
ekankthdevx/py_trans/language_codes.py
ekankthdevx/py_trans/translator.py
ekankthdevx/pyrogram/__init__.py
ekankthdevx/pyrogram/_wrappers.py
ekankthdevx/pyrogram/func.py
ekankthdevx/pyrogram/misc.py
ekankthdevx/pyrogram/sections.py
ekankthdevx/pyrogram/toolbot.py
ekankthdevx/pyrogram/tools.py